queenbee_pollination/__init__.py
queenbee_pollination/client.py
queenbee_pollination/config.py
queenbee_pollination/cli/__init__.py
queenbee_pollination/cli/context.py
queenbee_pollination/cli/project.py
queenbee_pollination/cli/pull.py
queenbee_pollination/cli/push.py
queenbee_pollination-0.7.10.dist-info/METADATA
queenbee_pollination-0.7.10.dist-info/WHEEL
queenbee_pollination-0.7.10.dist-info/entry_points.txt
queenbee_pollination-0.7.10.dist-info/top_level.txt
queenbee_pollination-0.7.10.dist-info/RECORD
