Metadata-Version: 2.1
Name: queenbee_pollination
Version: 0.7.10
Summary: queenbee-pollination extends queenbee to interact with the Pollination API
Home-page: https://github.com/pollination/queenbee-pollination
Author: Ladybug Tools
Author-email: info@ladybug.tools
Classifier: Programming Language :: Python :: 3.7
Classifier: Programming Language :: Python :: Implementation :: CPython
Classifier: Operating System :: OS Independent
Requires-Dist: queenbee>=1.22.13
Requires-Dist: pollination-sdk==0.10.17
Requires-Dist: tabulate>=0.8.7
Requires-Dist: requests>=2.24.0
Provides-Extra: cli
Requires-Dist: click==8.1.7; extra == "cli"
Requires-Dist: click-plugins; extra == "cli"
